{
	"name": "header_2",
	"properties": {
		"linkedServiceName": {
			"referenceName": "mis_link_service_20250219",
			"type": "LinkedServiceReference"
		},
		"annotations": [],
		"type": "DelimitedText",
		"typeProperties": {
			"location": {
				"type": "AzureBlobStorageLocation",
				"fileName": "header.csv",
				"container": "input"
			},
			"columnDelimiter": ",",
			"rowDelimiter": "\n",
			"escapeChar": "\"",
			"firstRowAsHeader": false,
			"quoteChar": "\""
		},
		"schema": []
	},
	"type": "Microsoft.DataFactory/factories/datasets"
}